nthlayer/__init__.py
nthlayer/cache.py
nthlayer/cloudwatch.py
nthlayer/demo.py
nthlayer/logging.py
nthlayer/orchestrator.py
nthlayer/secrets.py
nthlayer/tracing.py
nthlayer/user_config.py
nthlayer/alertmanager/__init__.py
nthlayer/alertmanager/config.py
nthlayer/alerts/__init__.py
nthlayer/alerts/loader.py
nthlayer/alerts/models.py
nthlayer/alerts/validator.py
nthlayer/api/__init__.py
nthlayer/api/auth.py
nthlayer/api/deps.py
nthlayer/api/main.py
nthlayer/api/routes/__init__.py
nthlayer/api/routes/health.py
nthlayer/api/routes/teams.py
nthlayer/cli/__init__.py
nthlayer/cli/apply.py
nthlayer/cli/blast_radius.py
nthlayer/cli/dashboard.py
nthlayer/cli/dashboard_validate.py
nthlayer/cli/dependencies.py
nthlayer/cli/deploy.py
nthlayer/cli/deps.py
nthlayer/cli/drift.py
nthlayer/cli/environments.py
nthlayer/cli/generate.py
nthlayer/cli/generate_alerts.py
nthlayer/cli/generate_loki.py
nthlayer/cli/identity.py
nthlayer/cli/init.py
nthlayer/cli/lint.py
nthlayer/cli/migrate.py
nthlayer/cli/ownership.py
nthlayer/cli/pagerduty.py
nthlayer/cli/plan.py
nthlayer/cli/portfolio.py
nthlayer/cli/recommend_metrics.py
nthlayer/cli/recording_rules.py
nthlayer/cli/scorecard.py
nthlayer/cli/setup.py
nthlayer/cli/slo.py
nthlayer/cli/templates.py
nthlayer/cli/ux.py
nthlayer/cli/validate.py
nthlayer/cli/validate_metadata.py
nthlayer/cli/validate_slo.py
nthlayer/cli/validate_spec.py
nthlayer/cli/verify.py
nthlayer/cli/formatters/__init__.py
nthlayer/cli/formatters/json_fmt.py
nthlayer/cli/formatters/junit.py
nthlayer/cli/formatters/markdown.py
nthlayer/cli/formatters/models.py
nthlayer/cli/formatters/sarif.py
nthlayer/clients/__init__.py
nthlayer/clients/base.py
nthlayer/clients/cortex.py
nthlayer/clients/pagerduty.py
nthlayer/clients/slack.py
nthlayer/config/__init__.py
nthlayer/config/cli.py
nthlayer/config/integrations.py
nthlayer/config/loader.py
nthlayer/config/settings.py
nthlayer/config/secrets/__init__.py
nthlayer/config/secrets/backends.py
nthlayer/core/__init__.py
nthlayer-0.1.0a15.dist-info/METADATA
nthlayer-0.1.0a15.dist-info/WHEEL
nthlayer-0.1.0a15.dist-info/entry_points.txt
nthlayer-0.1.0a15.dist-info/top_level.txt
nthlayer-0.1.0a15.dist-info/RECORD
