Metadata-Version: 2.4
Name: nthlayer
Version: 0.1.0a15
Summary: NthLayer - The Missing Layer of Reliability
Requires-Python: >=3.11
Requires-Dist: grafana-foundation-sdk>=0.0.11
Requires-Dist: fastapi<1.0.0,>=0.111.0
Requires-Dist: uvicorn[standard]<0.41,>=0.27.0
Requires-Dist: mangum<0.20.0,>=0.17.0
Requires-Dist: pydantic<3.0.0,>=2.7.0
Requires-Dist: pydantic-settings<3.0.0,>=2.2.1
Requires-Dist: sqlalchemy<3.0.0,>=2.0.30
Requires-Dist: alembic<2.0.0,>=1.13.1
Requires-Dist: psycopg[binary]<4.0.0,>=3.2.0
Requires-Dist: redis<8.0.0,>=5.0.4
Requires-Dist: httpx<0.29.0,>=0.27.0
Requires-Dist: pagerduty<7.0.0,>=6.0.0
Requires-Dist: aioboto3<16.0.0,>=12.3.0
Requires-Dist: boto3<2.0.0,>=1.34.0
Requires-Dist: langgraph<2.0.0,>=1.0.0
Requires-Dist: langchain<0.4.0,>=0.3.0
Requires-Dist: structlog<25.0.0,>=24.1.0
Requires-Dist: orjson<4.0.0,>=3.10.0
Requires-Dist: python-json-logger<3.0.0,>=2.0.7
Requires-Dist: tenacity<10.0.0,>=8.2.3
Requires-Dist: circuitbreaker<3.0.0,>=2.0.0
Requires-Dist: aws-xray-sdk<3.0.0,>=2.12.0
Requires-Dist: PyJWT[crypto]<3.0.0,>=2.8.0
Requires-Dist: jwcrypto<2.0.0,>=1.5.6
Requires-Dist: pyyaml<7.0.0,>=6.0.1
Requires-Dist: rich<14.0.0,>=13.7.0
Requires-Dist: rich-argparse<2.0.0,>=1.4.0
Requires-Dist: questionary<3.0.0,>=2.0.0
Requires-Dist: scipy<2.0.0,>=1.11.0
Requires-Dist: numpy<3.0.0,>=1.24.0
Requires-Dist: cachetools<6.0.0,>=5.3.0
Requires-Dist: opentelemetry-semantic-conventions>=0.60b1
Provides-Extra: dev
Requires-Dist: pytest<10.0.0,>=8.2.0; extra == "dev"
Requires-Dist: pytest-asyncio<2.0.0,>=0.23.0; extra == "dev"
Requires-Dist: pytest-cov<8.0.0,>=5.0.0; extra == "dev"
Requires-Dist: respx<0.23.0,>=0.21.0; extra == "dev"
Requires-Dist: ruff<0.15.0,>=0.4.0; extra == "dev"
Requires-Dist: mypy<1.20.0,>=1.10.0; extra == "dev"
Requires-Dist: types-redis>=4.6.0; extra == "dev"
Requires-Dist: types-requests>=2.31.0; extra == "dev"
Requires-Dist: types-python-dateutil>=2.8.19; extra == "dev"
Requires-Dist: types-PyYAML>=6.0.0; extra == "dev"
Requires-Dist: anyio<5.0.0,>=4.3.0; extra == "dev"
Requires-Dist: aiosqlite<1.0.0,>=0.20.0; extra == "dev"
Requires-Dist: greenlet<4.0.0,>=3.0.0; extra == "dev"
Requires-Dist: kubernetes<36.0.0,>=28.0.0; extra == "dev"
Provides-Extra: docs
Requires-Dist: mkdocs-material>=9.5.0; extra == "docs"
Requires-Dist: mkdocs-minify-plugin>=0.8.0; extra == "docs"
Provides-Extra: drift-ml
Requires-Dist: scikit-learn<2.0.0,>=1.3.0; extra == "drift-ml"
Provides-Extra: kubernetes
Requires-Dist: kubernetes<36.0.0,>=28.0.0; extra == "kubernetes"
Provides-Extra: zookeeper
Requires-Dist: kazoo<3.0.0,>=2.9.0; extra == "zookeeper"
Provides-Extra: etcd
Requires-Dist: etcd3<1.0.0,>=0.12.0; extra == "etcd"
Provides-Extra: service-discovery
Requires-Dist: kazoo<3.0.0,>=2.9.0; extra == "service-discovery"
Requires-Dist: etcd3<1.0.0,>=0.12.0; extra == "service-discovery"
